gpt_router/__init__.py
gpt_router/client.py
gpt_router/constants.py
gpt_router/enums.py
gpt_router/exceptions.py
gpt_router/models.py
gptrouter-1.0.6.dist-info/licenses/LICENSE
gptrouter-1.0.6.dist-info/METADATA
gptrouter-1.0.6.dist-info/WHEEL
gptrouter-1.0.6.dist-info/top_level.txt
gptrouter-1.0.6.dist-info/RECORD
