Metadata-Version: 2.4
Name: GPTRouter
Version: 1.0.6
Summary: A Python package for working with GPTRouter APIs
Author-email: sirjanpreet@writesonic.com
Classifier: Development Status :: 3 - Alpha
Classifier: Intended Audience :: Developers
Classifier: Programming Language :: Python :: 3
Classifier: Programming Language :: Python :: 3.10
Classifier: Programming Language :: Python :: 3.11
License-File: LICENSE
Requires-Dist: httpx>=0.23.3
Requires-Dist: pydantic>=2.0
Requires-Dist: pyhumps>=3.8.0
Dynamic: author-email
Dynamic: classifier
Dynamic: description
Dynamic: description-content-type
Dynamic: license-file
Dynamic: requires-dist
Dynamic: summary
